mcp_xiaozhi_server/__init__.py
mcp_xiaozhi_server/cli.py
mcp_xiaozhi_server/config.py
mcp_xiaozhi_server/controller.py
mcp_xiaozhi_server/main.py
mcp_xiaozhi_server-0.3.0.dist-info/METADATA
mcp_xiaozhi_server-0.3.0.dist-info/WHEEL
mcp_xiaozhi_server-0.3.0.dist-info/entry_points.txt
mcp_xiaozhi_server-0.3.0.dist-info/top_level.txt
mcp_xiaozhi_server-0.3.0.dist-info/RECORD
