Metadata-Version: 2.4
Name: mcp-xiaozhi-server
Version: 0.3.0
Summary: MCP 小智服务器 - 智能体管理工具
Home-page: https://github.com/104gogo/mcp-xiaozhi-server
Author: 104gogo
Author-email: Your Name <your.email@example.com>
License: MIT
Project-URL: Homepage, https://github.com/yourusername/mcp-xiaozhi-server
Project-URL: Repository, https://github.com/yourusername/mcp-xiaozhi-server
Project-URL: Issues, https://github.com/yourusername/mcp-xiaozhi-server/issues
Keywords: mcp,xiaozhi,agent,ai,server
Classifier: Development Status :: 3 - Alpha
Classifier: Intended Audience :: Developers
Classifier: License :: OSI Approved :: MIT License
Classifier: Operating System :: OS Independent
Classifier: Programming Language :: Python :: 3
Classifier: Programming Language :: Python :: 3.8
Classifier: Programming Language :: Python :: 3.9
Classifier: Programming Language :: Python :: 3.10
Classifier: Programming Language :: Python :: 3.11
Classifier: Programming Language :: Python :: 3.12
Requires-Python: >=3.8
Requires-Dist: mcp>=1.8.1
Requires-Dist: pydantic>=2.11.4
Requires-Dist: requests>=2.25.0
Dynamic: author
Dynamic: home-page
Dynamic: requires-python
